{
  "schema_id": "semantic-audit",
  "schema_version": "1.0.0",
  "contract_version": "v4",
  "run_id": "run-code005-example",
  "status": "done",
  "gate_check": {
    "status": "passed",
    "passed": true,
    "blockers": []
  },
  "path_policy": {
    "path_kind": "run_relative",
    "path_valid": false,
    "checked_path": "../outside-workspace.json"
  },
  "validation": {
    "schema_valid": true,
    "errors": []
  },
  "_code005_example_category": "path_negative",
  "_trace_refs": [
    "41-§2",
    "41-§12",
    "50-§3.5"
  ],
  "artifact": {
    "artifact_id": "ART-CODE005-001",
    "kind": "semantic_audit",
    "path": "logs/example.json",
    "path_kind": "run_relative",
    "schema_id": "semantic-audit",
    "schema_version": "1.0.0",
    "sha256": "0000000000000000000000000000000000000000000000000000000000000000",
    "size_bytes": 123,
    "required": true,
    "producer_result_id": "RESULT-CODE005-001"
  },
  "source_refs": [
    {
      "source_ref_id": "SRC-CODE005-001",
      "artifact_id": "ART-CODE005-001",
      "schema_id": "semantic-audit",
      "item_type": "schema_example",
      "item_id": "ITEM-CODE005-001"
    }
  ],
  "evidence_refs": [
    "EV-CODE005-001"
  ],
  "generated_at": "2026-05-07T09:00:00+08:00"
}
